{
  "name": {
    "lastname": "Трифонова",
    "firstname": "Юлия",
    "additional": "Викторовна"
  },
  "organization": "ГУАП",
  "title": "менеджер компетенции, старший преподаватель кафедры вычислительных систем и сетей Института №4",
  "location": "БМ 13-48",
  "photo": "https://pro.guap.ru/avatars/1/946.jpg",
  "telephones": [
    {
      "type": "WORK",
      "number": "+7999999999"
    },
    {
      "type": "CELL",
      "number": "+7888999888"
    },
    {
      "type": "HOME",
      "number": "+7888000333"
    }
  ],
  "emails": [
    {
      "type": "WORK",
      "address": "WORK@guap.ru"
    },
    {
      "type": "HOME",
      "address": "HOME@guap.ru"
    }
  ],
  "url": "https://pro.guap.ru/professors",
  "socials": [
    {
      "type": "Telegram",
      "userID": "testTG",
    },
    {
      "type": "VK",
      "userID": "testVK",
    },
    {
      "type": "OK",
      "userID": "testOK",
    }
  ]
}
